{
    "tab1" : "HOME",
    "tab2" : "BOTARMY",
    "tab3" : "RUNTIME",
    "home1" : "News",
    "home2" : "Bots",
    "wbIntro" : "Hello I am the Welcome Bot",
    "faqIntro" : "Hello I am the F.A.Q. Bot",
    "more" : "MORE",
    "language" : "Language",
    "welcomeMessage" : "Welcome Message",
    "options" : "Options",
    "welcomeBot" : "Welcome Bot",
    "faqBot" : "F.A.Q. Bot",
    "chooseTemplate" : "Choose a Template",
    "chooseName" : "Choose a Name for your ",
    "assign" : "Assign Chatbot",
    "chooseLanguage" :"Choose a language",
    "english" : "English",
    "german" : "German",
    "next" : "Next",
    "setMenu" : "Set Selection Menu",
    "deploy" : "Deploy",
    "lastEdit" : "Last Edit",
    "searchBy" : "Search by Botname"
}